CONTRIBUTING.md
LICENSE
MANIFEST.in
README.rst
setup.py
buildtest/__init__.py
buildtest/__pycache__/__init__.cpython-37.pyc
buildtest/ebapps/anaconda2/5.1.0/command.yaml
buildtest/ebapps/anaconda3/5.1.0/command.yaml
buildtest/ebapps/autoconf/2.69/command.yaml
buildtest/ebapps/automake/1.15.1/command.yaml
buildtest/ebapps/bamtools/2.5.1/command.yaml
buildtest/ebapps/bedtools/2.27.1/command.yaml
buildtest/ebapps/binutils/2.28/command.yaml
buildtest/ebapps/bison/3.0.4/command.yaml
buildtest/ebapps/bowtie2/2.3.4/command.yaml
buildtest/ebapps/bwa/0.7.17/command.yaml
buildtest/ebapps/bzip2/1.0.6/command.yaml
buildtest/ebapps/cairo/1.14.10/command.yaml
buildtest/ebapps/cmake/3.9.1/command.yaml
buildtest/ebapps/cmake/3.9.5/command.yaml
buildtest/ebapps/cp2k/5.1/command.yaml
buildtest/ebapps/cuda/7.5.18/command.yaml
buildtest/ebapps/cuda/8.0.61/command.yaml
buildtest/ebapps/cuda/9.1.85/command.yaml
buildtest/ebapps/curl/7.56.1/command.yaml
buildtest/ebapps/doxygen/1.8.13/command.yaml
buildtest/ebapps/easybuild/3.5.3/command.yaml
buildtest/ebapps/easybuild/3.6.0/command.yaml
buildtest/ebapps/expat/2.2.4/command.yaml
buildtest/ebapps/fftw/3.3.6/command.yaml
buildtest/ebapps/fftw/3.3.7/command.yaml
buildtest/ebapps/flex/2.6.3/command.yaml
buildtest/ebapps/flex/2.6.4/command.yaml
buildtest/ebapps/fltk/1.3.4/command.yaml
buildtest/ebapps/fontconfig/2.12.4/command.yaml
buildtest/ebapps/freetype/2.8/command.yaml
buildtest/ebapps/gcccore/6.4.0/command.yaml
buildtest/ebapps/gdal/2.2.2/command.yaml
buildtest/ebapps/geos/3.6.2/command.yaml
buildtest/ebapps/gettext/0.19.8.1/command.yaml
buildtest/ebapps/git-lfs/2.4.0/command.yaml
buildtest/ebapps/git/2.16.1/command.yaml
buildtest/ebapps/glib/2.53.5/command.yaml
buildtest/ebapps/glpk/4.61/command.yaml
buildtest/ebapps/gperf/3.1/command.yaml
buildtest/ebapps/gromacs/2016.5/command.yaml
buildtest/ebapps/gsl/2.4/command.yaml
buildtest/ebapps/guile/1.8.8/command.yaml
buildtest/ebapps/hdf5/1.10.1/command.yaml
buildtest/system/shared-mime-info/command.yaml
buildtest_configs.egg-info/PKG-INFO
buildtest_configs.egg-info/SOURCES.txt
buildtest_configs.egg-info/dependency_links.txt
buildtest_configs.egg-info/requires.txt
buildtest_configs.egg-info/top_level.txt